GeneGrouper/__init__.py
GeneGrouper/__main__.py
GeneGrouper/build_GenomeDatabase.py
GeneGrouper/build_QueryFiles.py
GeneGrouper/cluster_RegionSeqs.py
GeneGrouper/cluster_Regions.py
GeneGrouper/gtr_utils.py
GeneGrouper/make_Visualizations.py
GeneGrouper/output_RegionResults.py
GeneGrouper/Rscripts/visualize_group.R
GeneGrouper/Rscripts/visualize_main_region.R
GeneGrouper/Rscripts/visualize_tree.R
GeneGrouper-1.0.3.dist-info/LICENSE
GeneGrouper-1.0.3.dist-info/METADATA
GeneGrouper-1.0.3.dist-info/WHEEL
GeneGrouper-1.0.3.dist-info/entry_points.txt
GeneGrouper-1.0.3.dist-info/top_level.txt
GeneGrouper-1.0.3.dist-info/RECORD
