Metadata-Version: 2.1
Name: GeneGrouper
Version: 1.0.3
Summary: Find and cluster genomic regions containing a seed gene
Home-page: https://github.com/agmcfarland/GeneGrouper
Author: Alexander G. McFarland
Author-email: alexandermcfarland2022@u.northwestern.edu
License: UNKNOWN
Project-URL: Bug Tracker, https://github.com/agmcfarland/GeneGrouper/issues
Platform: UNKNOWN
Classifier: Programming Language :: Python :: 3
Classifier: License :: OSI Approved :: MIT License
Classifier: Operating System :: OS Independent
Classifier: Intended Audience :: Science/Research
Classifier: Topic :: Scientific/Engineering :: Bio-Informatics
Requires-Python: >=3.6
License-File: LICENSE
